<PAMDataset>
  <Metadata domain="IMAGE_STRUCTURE">
    <MDI key="COMPRESSION">JPEG</MDI>
    <MDI key="INTERLEAVE">PIXEL</MDI>
    <MDI key="SOURCE_COLOR_SPACE">YCbCr</MDI>
  </Metadata>
  <Metadata>
    <MDI key="EXIF_Artist">Unknown</MDI>
    <MDI key="EXIF_ColorSpace">1</MDI>
    <MDI key="EXIF_DateTime">2023:11:28 18:28:19</MDI>
    <MDI key="EXIF_DateTimeDigitized">2023:11:28 16:27:36</MDI>
    <MDI key="EXIF_ExifVersion">0221</MDI>
    <MDI key="EXIF_Orientation">1</MDI>
    <MDI key="EXIF_PhotometricInterpretation">2</MDI>
    <MDI key="EXIF_PixelXDimension">4077</MDI>
    <MDI key="EXIF_PixelYDimension">2019</MDI>
    <MDI key="EXIF_ResolutionUnit">2</MDI>
    <MDI key="EXIF_Software">Adobe Photoshop CS5.1 Macintosh</MDI>
    <MDI key="EXIF_XResolution">(300)</MDI>
    <MDI key="EXIF_YResolution">(300)</MDI>
  </Metadata>
  <PAMRasterBand band="1">
    <Metadata domain="IMAGE_STRUCTURE">
      <MDI key="COMPRESSION">JPEG</MDI>
    </Metadata>
    <Metadata>
      <MDI key="STATISTICS_APPROXIMATE">YES</MDI>
      <MDI key="STATISTICS_MAXIMUM">255</MDI>
      <MDI key="STATISTICS_MEAN">209.38739052933</MDI>
      <MDI key="STATISTICS_MINIMUM">58</MDI>
      <MDI key="STATISTICS_STDDEV">17.039104443836</MDI>
      <MDI key="STATISTICS_VALID_PERCENT">100</MDI>
    </Metadata>
  </PAMRasterBand>
  <PAMRasterBand band="2">
    <Metadata domain="IMAGE_STRUCTURE">
      <MDI key="COMPRESSION">JPEG</MDI>
    </Metadata>
    <Metadata>
      <MDI key="STATISTICS_APPROXIMATE">YES</MDI>
      <MDI key="STATISTICS_MAXIMUM">217</MDI>
      <MDI key="STATISTICS_MEAN">189.58383321708</MDI>
      <MDI key="STATISTICS_MINIMUM">56</MDI>
      <MDI key="STATISTICS_STDDEV">17.641757134498</MDI>
      <MDI key="STATISTICS_VALID_PERCENT">100</MDI>
    </Metadata>
  </PAMRasterBand>
  <PAMRasterBand band="3">
    <Metadata domain="IMAGE_STRUCTURE">
      <MDI key="COMPRESSION">JPEG</MDI>
    </Metadata>
    <Metadata>
      <MDI key="STATISTICS_APPROXIMATE">YES</MDI>
      <MDI key="STATISTICS_MAXIMUM">187</MDI>
      <MDI key="STATISTICS_MEAN">157.56290010075</MDI>
      <MDI key="STATISTICS_MINIMUM">47</MDI>
      <MDI key="STATISTICS_STDDEV">15.848526141182</MDI>
      <MDI key="STATISTICS_VALID_PERCENT">100</MDI>
    </Metadata>
  </PAMRasterBand>
</PAMDataset>
