<PAMDataset>
  <Metadata domain="IMAGE_STRUCTURE">
    <MDI key="COMPRESSION">JPEG</MDI>
    <MDI key="INTERLEAVE">PIXEL</MDI>
    <MDI key="SOURCE_COLOR_SPACE">YCbCr</MDI>
  </Metadata>
  <Metadata domain="xml:ESRI" format="xml">
    <GeodataXform xsi:type="typens:PolynomialXform" xmlns:xsi="http://www.w3.org/2001/XMLSchema-instance" xmlns:xs="http://www.w3.org/2001/XMLSchema" xmlns:typens="http://www.esri.com/schemas/ArcGIS/3.3.0">
      <PolynomialOrder>-4</PolynomialOrder>
      <SpatialReference xsi:type="typens:ProjectedCoordinateSystem">
        <WKT>PROJCS["WGS_1984_Web_Mercator_Auxiliary_Sphere",GEOGCS["GCS_WGS_1984",DATUM["D_WGS_1984",SPHEROID["WGS_1984",6378137.0,298.257223563]],PRIMEM["Greenwich",0.0],UNIT["Degree",0.0174532925199433]],PROJECTION["Mercator_Auxiliary_Sphere"],PARAMETER["False_Easting",0.0],PARAMETER["False_Northing",0.0],PARAMETER["Central_Meridian",0.0],PARAMETER["Standard_Parallel_1",0.0],PARAMETER["Auxiliary_Sphere_Type",0.0],UNIT["Meter",1.0],AUTHORITY["EPSG",3857]]</WKT>
        <XOrigin>-20037700</XOrigin>
        <YOrigin>-30241100</YOrigin>
        <XYScale>148923141.92838538</XYScale>
        <ZOrigin>-100000</ZOrigin>
        <ZScale>10000</ZScale>
        <MOrigin>-100000</MOrigin>
        <MScale>10000</MScale>
        <XYTolerance>0.001</XYTolerance>
        <ZTolerance>0.001</ZTolerance>
        <MTolerance>0.001</MTolerance>
        <HighPrecision>true</HighPrecision>
        <WKID>102100</WKID>
        <LatestWKID>3857</LatestWKID>
      </SpatialReference>
      <SourceGCPs xsi:type="typens:ArrayOfDouble">
        <Double>4700.556865199208</Double>
        <Double>-3335.0388516423718</Double>
        <Double>3292.3233457905044</Double>
        <Double>-3828.6880006728898</Double>
        <Double>2952.224874895066</Double>
        <Double>-2836.5285695977509</Double>
        <Double>3784.8967357650399</Double>
        <Double>-1932.7235894100741</Double>
        <Double>4706.1676187301055</Double>
        <Double>-1438.0242173457518</Double>
        <Double>1792.966395823285</Double>
        <Double>-3331.6938515864313</Double>
      </SourceGCPs>
      <TargetGCPs xsi:type="typens:ArrayOfDouble">
        <Double>-8226200.1701181848</Double>
        <Double>4959835.8388797119</Double>
        <Double>-8226682.4763856214</Double>
        <Double>4959012.386207249</Double>
        <Double>-8227261.3616450485</Double>
        <Double>4959349.2977798032</Double>
        <Double>-8227219.4298910471</Double>
        <Double>4960134.2821879033</Double>
        <Double>-8226974.7853151113</Double>
        <Double>4960754.8394596428</Double>
        <Double>-8227618.4224325307</Double>
        <Double>4958628.4927594215</Double>
      </TargetGCPs>
      <Name />
    </GeodataXform>
  </Metadata>
  <PAMRasterBand band="1">
    <Histograms>
      <HistItem>
        <HistMin>-0.5</HistMin>
        <HistMax>255.5</HistMax>
        <BucketCount>256</BucketCount>
        <IncludeOutOfRange>1</IncludeOutOfRange>
        <Approximate>0</Approximate>
        <HistCounts>0|0|0|0|0|0|0|0|0|0|0|0|0|0|0|0|0|0|0|0|0|0|0|0|0|0|0|0|0|0|0|0|0|0|0|0|0|0|0|0|0|0|0|1|0|7|5|12|12|15|15|17|17|32|38|40|37|52|52|84|96|110|134|193|207|265|296|401|487|639|842|990|1227|1521|1907|2323|2844|3311|3885|4392|5108|5779|6389|6973|7819|8398|8761|9560|10131|10428|10857|11546|12066|12722|13462|14231|15229|16675|18253|20396|22762|25626|28505|31475|34399|36649|38329|39359|39586|40370|39930|39677|40277|40869|41124|41837|42628|42416|42582|42359|42100|41343|40774|39522|38703|38059|37257|36463|36057|35705|35745|36215|36697|37171|38270|39850|40679|41717|42276|42442|42215|41247|40162|38290|36451|34404|32680|31232|29516|28957|27499|26475|26014|25537|25942|25639|26317|26322|27229|27814|28620|29148|29961|30542|31434|32303|33292|33387|34690|35729|36473|37817|38452|39432|40180|40491|41253|42133|42582|43319|43135|43846|43901|43712|44097|43932|44023|44106|44374|44448|44646|45370|46140|46828|48010|48754|50157|51812|53608|56629|59498|62993|66274|70335|72841|76625|79616|83230|85927|86862|87019|86610|86380|86401|86083|86649|87434|89187|93164|99242|106551|118123|134310|153707|178211|209708|252221|305131|371282|460888|580269|750650|986475|1294713|1596819|1763628|1812070|1747952|1580544|1344191|1088454|839563|666029|517381|371792|251422|166069|113304|75299|46227|26707|15006|8380|4563|2661|5059</HistCounts>
      </HistItem>
    </Histograms>
    <Metadata domain="IMAGE_STRUCTURE">
      <MDI key="COMPRESSION">JPEG</MDI>
    </Metadata>
    <Metadata>
      <MDI key="STATISTICS_COUNT">25629530.000000</MDI>
      <MDI key="STATISTICS_COVARIANCES">1217.813148950992,1075.975695333558,933.746869421803</MDI>
      <MDI key="STATISTICS_MAXIMUM">255</MDI>
      <MDI key="STATISTICS_MEAN">220.0733158977</MDI>
      <MDI key="STATISTICS_MEDIAN">234.000000</MDI>
      <MDI key="STATISTICS_MINIMUM">43</MDI>
      <MDI key="STATISTICS_SKIPFACTORX">1</MDI>
      <MDI key="STATISTICS_SKIPFACTORY">1</MDI>
      <MDI key="STATISTICS_STDDEV">34.89717967044</MDI>
    </Metadata>
  </PAMRasterBand>
  <PAMRasterBand band="2">
    <Histograms>
      <HistItem>
        <HistMin>-0.5</HistMin>
        <HistMax>255.5</HistMax>
        <BucketCount>256</BucketCount>
        <IncludeOutOfRange>1</IncludeOutOfRange>
        <Approximate>0</Approximate>
        <HistCounts>0|0|0|0|0|0|0|0|0|0|0|0|0|0|0|0|0|0|0|0|0|0|0|0|0|0|0|0|0|0|0|0|0|0|0|0|0|1|1|2|1|7|4|4|8|10|17|22|25|26|30|47|46|77|69|121|161|228|276|390|549|662|862|1178|1501|1967|2576|3030|3623|4525|5215|6243|7009|7757|8564|9389|9886|10818|11275|11822|12095|12598|12773|13227|13436|13728|13860|13907|14145|14361|14662|15047|15836|16766|18319|20394|22964|26120|30112|34072|37235|39950|42028|42598|42360|41335|40588|40212|40502|41247|42341|43671|45238|45763|46279|46287|45747|45136|44366|43335|43158|42284|41167|40609|40533|40718|40723|41645|42548|43463|44661|46406|47029|47840|48060|47186|46629|44957|42273|39418|36669|34260|32110|30598|29443|28649|28822|28862|29175|29567|30309|30768|31554|32578|33677|34664|35970|37683|39199|40778|42763|44362|45875|47242|48678|49687|51263|52335|53798|55299|56160|57538|58997|60842|62286|63986|65412|66473|66963|69013|69601|70254|72181|73325|75402|77025|79747|82996|86694|90375|94801|98791|103331|108819|114109|120590|126216|131448|137228|145177|155822|171898|193700|224277|264527|313335|371651|430085|488476|537233|567491|587233|614525|653980|691446|729995|773308|828414|896660|998750|1116664|1156346|1047958|959967|975211|991303|883327|629129|426784|326974|269232|201148|121116|59401|26142|11811|5865|2955|1743|1091|751|543|389|316|270|200|158|154|131|136|150|150|219|304|247|51</HistCounts>
      </HistItem>
    </Histograms>
    <Metadata domain="IMAGE_STRUCTURE">
      <MDI key="COMPRESSION">JPEG</MDI>
    </Metadata>
    <Metadata>
      <MDI key="STATISTICS_COUNT">25629530.000000</MDI>
      <MDI key="STATISTICS_COVARIANCES">1075.975695333558,1064.668094864865,979.7801855542892</MDI>
      <MDI key="STATISTICS_MAXIMUM">255</MDI>
      <MDI key="STATISTICS_MEAN">203.00708982962</MDI>
      <MDI key="STATISTICS_MEDIAN">215.000000</MDI>
      <MDI key="STATISTICS_MINIMUM">37</MDI>
      <MDI key="STATISTICS_SKIPFACTORX">1</MDI>
      <MDI key="STATISTICS_SKIPFACTORY">1</MDI>
      <MDI key="STATISTICS_STDDEV">32.629252134624</MDI>
    </Metadata>
  </PAMRasterBand>
  <PAMRasterBand band="3">
    <Histograms>
      <HistItem>
        <HistMin>-0.5</HistMin>
        <HistMax>255.5</HistMax>
        <BucketCount>256</BucketCount>
        <IncludeOutOfRange>1</IncludeOutOfRange>
        <Approximate>0</Approximate>
        <HistCounts>0|0|0|0|0|2|0|2|2|0|3|1|0|4|3|7|7|8|12|14|18|19|17|31|23|40|31|32|48|62|71|66|74|113|110|122|139|163|192|237|272|333|338|372|453|524|641|766|925|940|1209|1373|1572|1901|2155|2603|3041|3431|4061|4726|5423|6343|7159|7801|8636|9613|10191|11084|11662|12157|12801|13091|13404|13964|14330|14813|14851|15455|15502|15854|15934|16046|16162|16674|16806|17132|17603|17914|18859|18946|20051|21600|22877|24750|27273|30115|33628|36926|40106|43205|45507|47124|47961|48298|47820|47969|47230|47653|47871|48580|50429|51337|53133|54730|56799|58218|58358|59368|59635|59992|58918|59122|57672|56937|56520|55975|55237|54952|55499|56133|57431|58068|59563|60852|61497|61084|60131|58435|55659|52576|50413|48206|46191|44230|43054|42247|41756|41702|42157|42405|43449|45013|45686|47754|49462|50756|52449|54863|56415|58943|61457|64142|66939|71292|76105|81269|86030|92240|98656|106854|116072|127041|140347|157813|177489|201561|231601|261842|289574|318294|337700|348982|358884|366239|377739|389677|399315|402583|400879|385351|368436|352711|353699|361047|367182|381875|407692|439593|456136|472105|490323|514619|561195|630613|715441|791480|758642|715016|696788|714402|762988|780409|691749|537626|409573|349232|284823|236052|201388|155588|100101|51924|23124|10521|5005|2526|1404|865|524|382|261|179|198|157|105|124|100|88|65|74|65|79|56|71|68|68|58|63|70|59|70|98|70|132|52|860</HistCounts>
      </HistItem>
    </Histograms>
    <Metadata domain="IMAGE_STRUCTURE">
      <MDI key="COMPRESSION">JPEG</MDI>
    </Metadata>
    <Metadata>
      <MDI key="STATISTICS_COUNT">25629530.000000</MDI>
      <MDI key="STATISTICS_COVARIANCES">933.746869421803,979.7801855542892,1007.524445593597</MDI>
      <MDI key="STATISTICS_MAXIMUM">255</MDI>
      <MDI key="STATISTICS_MEAN">185.52437532019</MDI>
      <MDI key="STATISTICS_MEDIAN">196.000000</MDI>
      <MDI key="STATISTICS_MINIMUM">5</MDI>
      <MDI key="STATISTICS_SKIPFACTORX">1</MDI>
      <MDI key="STATISTICS_SKIPFACTORY">1</MDI>
      <MDI key="STATISTICS_STDDEV">31.741525571302</MDI>
    </Metadata>
  </PAMRasterBand>
</PAMDataset>
